py_screen_grab/__init__.py
py_screen_grab/cli.py
py_screen_grab/screen_grabber.py
py_screen_grab/window_utils.py
py_screen_grab-1.5.0.dist-info/licenses/LICENSE
py_screen_grab-1.5.0.dist-info/METADATA
py_screen_grab-1.5.0.dist-info/WHEEL
py_screen_grab-1.5.0.dist-info/entry_points.txt
py_screen_grab-1.5.0.dist-info/top_level.txt
py_screen_grab-1.5.0.dist-info/RECORD
